pyston_lite.cpython-39-aarch64-linux-gnu.so
pyston_lite-2.3.5.dist-info/WHEEL
pyston_lite-2.3.5.dist-info/RECORD
pyston_lite-2.3.5.dist-info/top_level.txt
pyston_lite-2.3.5.dist-info/METADATA
