Metadata-Version: 2.1
Name: pyston-lite
Version: 2.3.5
Summary: A JIT for Python
Home-page: https://www.github.com/pyston/pyston
Author: The Pyston Team
